odoo/addons/cms_status_message/README.rst
odoo/addons/cms_status_message/__init__.py
odoo/addons/cms_status_message/__manifest__.py
odoo/addons/cms_status_message/controllers/__init__.py
odoo/addons/cms_status_message/controllers/main.py
odoo/addons/cms_status_message/i18n/ca.po
odoo/addons/cms_status_message/i18n/cms_status_message.pot
odoo/addons/cms_status_message/i18n/es.po
odoo/addons/cms_status_message/i18n/fr.po
odoo/addons/cms_status_message/i18n/it.po
odoo/addons/cms_status_message/images/preview.png
odoo/addons/cms_status_message/models/__init__.py
odoo/addons/cms_status_message/models/website.py
odoo/addons/cms_status_message/readme/CONTRIBUTORS.rst
odoo/addons/cms_status_message/readme/DESCRIPTION.rst
odoo/addons/cms_status_message/readme/HISTORY.rst
odoo/addons/cms_status_message/readme/ROADMAP.rst
odoo/addons/cms_status_message/readme/USAGE.rst
odoo/addons/cms_status_message/static/description/icon.png
odoo/addons/cms_status_message/static/description/index.html
odoo/addons/cms_status_message/static/src/js/autodismiss.js
odoo/addons/cms_status_message/static/src/js/tool.js
odoo/addons/cms_status_message/templates/assets.xml
odoo/addons/cms_status_message/templates/display_test.xml
odoo/addons/cms_status_message/templates/status_message.xml
odoo/addons/cms_status_message/tests/__init__.py
odoo/addons/cms_status_message/tests/test_message.py
odoo13_addon_cms_status_message-13.0.1.0.1.dist-info/METADATA
odoo13_addon_cms_status_message-13.0.1.0.1.dist-info/WHEEL
odoo13_addon_cms_status_message-13.0.1.0.1.dist-info/top_level.txt
odoo13_addon_cms_status_message-13.0.1.0.1.dist-info/RECORD
